calculator_aura/.DS_Store
calculator_aura/__init__.py
calculator_aura/calculator.py
calculator_aura/.mypy_cache/.gitignore
calculator_aura/.mypy_cache/CACHEDIR.TAG
calculator_aura/.mypy_cache/3.11/@plugins_snapshot.json
calculator_aura/.mypy_cache/3.11/_ast.data.json
calculator_aura/.mypy_cache/3.11/_ast.meta.json
calculator_aura/.mypy_cache/3.11/_codecs.data.json
calculator_aura/.mypy_cache/3.11/_codecs.meta.json
calculator_aura/.mypy_cache/3.11/_collections_abc.data.json
calculator_aura/.mypy_cache/3.11/_collections_abc.meta.json
calculator_aura/.mypy_cache/3.11/abc.data.json
calculator_aura/.mypy_cache/3.11/abc.meta.json
calculator_aura/.mypy_cache/3.11/builtins.data.json
calculator_aura/.mypy_cache/3.11/builtins.meta.json
calculator_aura/.mypy_cache/3.11/codecs.data.json
calculator_aura/.mypy_cache/3.11/codecs.meta.json
calculator_aura/.mypy_cache/3.11/contextlib.data.json
calculator_aura/.mypy_cache/3.11/contextlib.meta.json
calculator_aura/.mypy_cache/3.11/dataclasses.data.json
calculator_aura/.mypy_cache/3.11/dataclasses.meta.json
calculator_aura/.mypy_cache/3.11/enum.data.json
calculator_aura/.mypy_cache/3.11/enum.meta.json
calculator_aura/.mypy_cache/3.11/genericpath.data.json
calculator_aura/.mypy_cache/3.11/genericpath.meta.json
calculator_aura/.mypy_cache/3.11/io.data.json
calculator_aura/.mypy_cache/3.11/io.meta.json
calculator_aura/.mypy_cache/3.11/pathlib.data.json
calculator_aura/.mypy_cache/3.11/pathlib.meta.json
calculator_aura/.mypy_cache/3.11/posixpath.data.json
calculator_aura/.mypy_cache/3.11/posixpath.meta.json
calculator_aura/.mypy_cache/3.11/re.data.json
calculator_aura/.mypy_cache/3.11/re.meta.json
calculator_aura/.mypy_cache/3.11/resource.data.json
calculator_aura/.mypy_cache/3.11/resource.meta.json
calculator_aura/.mypy_cache/3.11/sre_compile.data.json
calculator_aura/.mypy_cache/3.11/sre_compile.meta.json
calculator_aura/.mypy_cache/3.11/sre_constants.data.json
calculator_aura/.mypy_cache/3.11/sre_constants.meta.json
calculator_aura-0.0.2.dist-info/LICENSE
calculator_aura-0.0.2.dist-info/WHEEL
calculator_aura-0.0.2.dist-info/METADATA
calculator_aura-0.0.2.dist-info/RECORD
