Metadata-Version: 2.1
Name: calculator_aura
Version: 0.0.2
Summary: Python package performing simple calculator functions
Author-email: Aura Milasiute <milasiute.aura@gmail.com>
Requires-Python: >=3.6
Classifier: License :: OSI Approved :: MIT License
Project-URL: Homepage, https://github.com/auramila/calculator
